pdfminer/__init__.py
pdfminer/arcfour.py
pdfminer/ascii85.py
pdfminer/ccitt.py
pdfminer/cmapdb.py
pdfminer/converter.py
pdfminer/encodingdb.py
pdfminer/fontmetrics.py
pdfminer/glyphlist.py
pdfminer/high_level.py
pdfminer/image.py
pdfminer/jbig2.py
pdfminer/latin_enc.py
pdfminer/layout.py
pdfminer/lzw.py
pdfminer/pdfcolor.py
pdfminer/pdfdevice.py
pdfminer/pdfdocument.py
pdfminer/pdffont.py
pdfminer/pdfinterp.py
pdfminer/pdfpage.py
pdfminer/pdfparser.py
pdfminer/pdftypes.py
pdfminer/psparser.py
pdfminer/rijndael.py
pdfminer/runlength.py
pdfminer/settings.py
pdfminer/utils.py
tools/Makefile
tools/__init__.py
tools/conv_afm.py
tools/conv_cmap.py
tools/conv_glyphlist.py
tools/dumppdf.py
tools/latin2ascii.py
tools/pdf2html.cgi
tools/pdf2txt.py
tools/pdf2txt.spec
tools/pdfdiff.py
tools/pdfdiff.spec
tools/pdfstats.py
tools/prof.py
tools/runapp.py
yapdfminer-1.2.2.data/scripts/dumppdf.py
yapdfminer-1.2.2.data/scripts/latin2ascii.py
yapdfminer-1.2.2.data/scripts/pdf2txt.py
yapdfminer-1.2.2.dist-info/LICENSE
yapdfminer-1.2.2.dist-info/METADATA
yapdfminer-1.2.2.dist-info/WHEEL
yapdfminer-1.2.2.dist-info/top_level.txt
yapdfminer-1.2.2.dist-info/RECORD
