Metadata-Version: 2.1
Name: yapdfminer
Version: 1.2.2
Summary: PDF parser and analyzer
Home-page: https://github.com/eladkehat/yapdfminer
Author: Elad Kehat
Author-email: eladkehat@gmail.com
License: MIT
Keywords: pdf,pdf parser,pdf converter,layout analysis,text mining
Platform: UNKNOWN
Classifier: Development Status :: 5 - Production/Stable
Classifier: Environment :: Console
Classifier: Intended Audience :: Developers
Classifier: Intended Audience :: Science/Research
Classifier: License :: OSI Approved :: MIT License
Classifier: Operating System :: OS Independent
Classifier: Programming Language :: Python :: 3.7
Classifier: Topic :: Text Processing
Requires-Python: >=3.7
